{
  "project_info": {
    "project_number": "255736834120",
    "project_id": "interview-demo-application",
    "storage_bucket": "interview-demo-application.appspot.com"
  },
  "client": [
    {
      "client_info": {
        "mobilesdk_app_id": "1:255736834120:android:1e9a6b6f79290ed053507d",
        "android_client_info": {
          "package_name": "com.example.interview_demo_application"
        }
      },
      "oauth_client": [
        {
          "client_id": "255736834120-kcbhd2ge0v4vd0ld9n4t83gr00v0qk6a.apps.googleusercontent.com",
          "client_type": 3
        }
      ],
      "api_key": [
        {
          "current_key": "AIzaSyAkXXIhhWGTZWk3p8kIxRIh9CosOhEX4q8"
        }
      ],
      "services": {
        "appinvite_service": {
          "other_platform_oauth_client": [
            {
              "client_id": "255736834120-kcbhd2ge0v4vd0ld9n4t83gr00v0qk6a.apps.googleusercontent.com",
              "client_type": 3
            }
          ]
        }
      }
    }
  ],
  "configuration_version": "1"
}